flagsense/__init__.py
flagsense/__main__.py
flagsense/yolo_inference.py
flagsense-0.1.4.dist-info/licenses/LICENSE
flagsense-0.1.4.dist-info/METADATA
flagsense-0.1.4.dist-info/WHEEL
flagsense-0.1.4.dist-info/entry_points.txt
flagsense-0.1.4.dist-info/top_level.txt
flagsense-0.1.4.dist-info/RECORD
